resources/version.txt
versioning_remla/__init__.py
versioning_remla/versioning.py
versioning_remla-1.0.0.dist-info/LICENSE
versioning_remla-1.0.0.dist-info/METADATA
versioning_remla-1.0.0.dist-info/WHEEL
versioning_remla-1.0.0.dist-info/RECORD
